ValorantAPI_Wrapper/__init__.py
ValorantAPI_Wrapper/auth.py
ValorantAPI_Wrapper/client.py
ValorantAPI_Wrapper/exceptions.py
ValorantAPI_Wrapper/resources.py
ValorantAPI_Wrapper/serverStatus.py
ValorantAPI_Wrapper-1.2.0.dist-info/LICENSE.md
ValorantAPI_Wrapper-1.2.0.dist-info/METADATA
ValorantAPI_Wrapper-1.2.0.dist-info/WHEEL
ValorantAPI_Wrapper-1.2.0.dist-info/top_level.txt
ValorantAPI_Wrapper-1.2.0.dist-info/RECORD
