Metadata-Version: 2.1
Name: ValorantAPI-Wrapper
Version: 1.2.0
Summary: Unofficial API wrappper for Valorant
Home-page: https://github.com/Csence/ValorantAPI_Wrapper
Author: Csence
Project-URL: Bug Tracker, https://github.com/Csence/ValorantAPI_Wrapper/issues
Keywords: Valorant,Python,API,valorant-api
Classifier: Programming Language :: Python :: 3
Classifier: License :: OSI Approved :: MIT License
Classifier: Operating System :: OS Independent
Requires-Python: >=3.0
License-File: LICENSE.md
